{
    "$schema": "../../schema/list.json",
    "id": "vitallist.xyz",
    "added": 1668474333,
    "name": "VitalList",
    "url": "https://vitallist.xyz/",
    "icon": "https://vitallist.xyz/img/icon.webp",
    "language": "English",
    "display": 1,
    "defunct": 1,
    "discord_only": 1,
    "description": "A place where you can find Discord bots, Vital List.|",
    "api_docs": "https://vitallist.xyz/docs/",
    "api_post": "https://vitallist.xyz/api/bots/:id",
    "api_post_method": null,
    "api_field": "server_count",
    "api_shard_id": null,
    "api_shard_count": "shard_count",
    "api_shards": null,
    "api_get": "https://vitallist.xyz/api/bots/:id",
    "api_all": null,
    "view_bot": "https://vitallist.xyz/bots/:id",
    "bot_widget": "https://vitallist.xyz/bots/:id/widget",
    "content": null,
    "owners": "BrydenIsNotSmart#0001 (529815278456930314), Kyasa#9048 (700609775838298113)",
    "discord": "https://vitallist.xyz/discord",
    "features": [
        "bot-resubmission",
        "bot-reviews",
        "html-long-description",
        "iframe-long-description",
        "markdown-long-description",
        "custom-bot-donate-link",
        "custom-bot-github-link",
        "custom-bot-invite-link",
        "custom-bot-support-link",
        "custom-bot-website-link",
        "has-voting",
        "votes-sent-to-webhooks",
        "has-categories-or-tags",
        "has-mobile-support",
        "server-count-api"
    ]
}
